slotted_aloha_simulator/__init__.py
slotted_aloha_simulator/jit.py
slotted_aloha_simulator/parallel.py
slotted_aloha_simulator/plot.py
slotted_aloha_simulator/slotted_aloha_simulator.py
slotted_aloha_simulator-0.1.0.dist-info/AUTHORS.md
slotted_aloha_simulator-0.1.0.dist-info/LICENSE
slotted_aloha_simulator-0.1.0.dist-info/METADATA
slotted_aloha_simulator-0.1.0.dist-info/WHEEL
slotted_aloha_simulator-0.1.0.dist-info/RECORD
