Metadata-Version: 2.1
Name: slotted-aloha-simulator
Version: 0.1.0
Summary: SAS provides simulation and mean field models for slotted Aloha with talkative users.
Home-page: https://github.com/balouf/slotted-aloha-simulator
Author: Fabien Mathieu
Author-email: loufab@gmail.com
Requires-Python: >=3.9,<4.0
Classifier: Programming Language :: Python :: 3
Classifier: Programming Language :: Python :: 3.9
Classifier: Programming Language :: Python :: 3.10
Classifier: Programming Language :: Python :: 3.11
Classifier: Programming Language :: Python :: 3.12
Requires-Dist: joblib (>=1.3.2,<2.0.0)
Requires-Dist: matplotlib (==3.7.1)
Requires-Dist: numba (>=0.59.0,<0.60.0)
Requires-Dist: scipy (>=1.12.0,<2.0.0)
Requires-Dist: tikzplotlib (>=0.10.1,<0.11.0)
Project-URL: Documentation, https://balouf.github.io/slotted-aloha-simulator
Project-URL: Repository, https://github.com/balouf/slotted-aloha-simulator
